tracerec/__init__.py
tracerec/algorithms/embedder.py
tracerec/algorithms/graph_based/__init__.py
tracerec/algorithms/graph_based/complex.py
tracerec/algorithms/graph_based/graph_embedder.py
tracerec/algorithms/graph_based/rotate.py
tracerec/algorithms/graph_based/simple.py
tracerec/algorithms/graph_based/transe.py
tracerec/algorithms/graph_based/transh.py
tracerec/algorithms/graph_based/transr.py
tracerec/algorithms/graph_based/tucker.py
tracerec/algorithms/sequential_based/__init__.py
tracerec/algorithms/sequential_based/caser.py
tracerec/algorithms/sequential_based/grurec.py
tracerec/algorithms/sequential_based/sasrec.py
tracerec/algorithms/sequential_based/sequential_embedder.py
tracerec/data/__init__.py
tracerec/data/datasets/__init__.py
tracerec/data/datasets/base_dataset.py
tracerec/data/datasets/path_dataset.py
tracerec/data/datasets/triples_dataset.py
tracerec/data/paths/__init__.py
tracerec/data/paths/path_manager.py
tracerec/data/triples/__init__.py
tracerec/data/triples/triples_manager.py
tracerec/losses/bpr.py
tracerec/losses/loss.py
tracerec/losses/supcon.py
tracerec/metrics/__init__.py
tracerec/metrics/map.py
tracerec/samplers/negative_triple_sampler.py
tracerec/samplers/path_based_sampler.py
tracerec/samplers/random_sampler.py
tracerec/utils/__init__.py
tracerec/utils/collates.py
tracerec-0.4.6.dist-info/METADATA
tracerec-0.4.6.dist-info/WHEEL
tracerec-0.4.6.dist-info/licenses/LICENSE
tracerec-0.4.6.dist-info/RECORD
