Metadata-Version: 2.4
Name: tracerec
Version: 0.4.6
Summary: Python package for the creation of recommendation systems based on user traces.
License: MIT
License-File: LICENSE
Author: Alex Martínez
Author-email: almtav08@gmail.com
Requires-Python: >=3.9
Classifier: Programming Language :: Python :: 3
Classifier: License :: OSI Approved :: MIT License
Classifier: Operating System :: OS Independent
Requires-Dist: networkx (>=2.6.0)
Requires-Dist: numpy (>=2.0.0)
Requires-Dist: torch (>=2.0.0)
Project-URL: Bug Tracker, https://github.com/almtav08/tracerec/issues
Project-URL: Homepage, https://github.com/almtav08/tracerec
